[
    {
        "url": "https://github.com/linhd-postdata/biblioteca_italiana/blob/master/xml/bibit000936",
        "author": "Niccolò de' Ricci",
        "collection": "Poesie",
        "title": "I",
        "manually_checked": false,
        "text": [
            [
                {
                    "verse": "Poi che Fortuna, Destino ed Amore"
                },
                {
                    "verse": "m'hanno condotto al doloroso punto"
                },
                {
                    "verse": "ove il vero è dispunto,"
                },
                {
                    "verse": "ché giunto è 'l sezzo punto — a mezzo il core,"
                },
                {
                    "verse": "piangendo priego e priego te, Signore,"
                },
                {
                    "verse": "anzi che' sensi miei sien tutti ispersi,"
                },
                {
                    "verse": "ch'io possa dir per versi"
                },
                {
                    "verse": "quel che drento nel cor per me si sente,"
                },
                {
                    "verse": "acciò ch'a tutta gente"
                },
                {
                    "verse": "sia manifesto poi, quand' io son morto,"
                },
                {
                    "verse": "ch'una donna m'ancise e femmi torto."
                }
            ],
            [
                {
                    "verse": "Quando da prima quella gran beltade"
                },
                {
                    "verse": "vidi in colei, ove tutto s'accolse,"
                },
                {
                    "verse": "quantunque al mondo tolse"
                },
                {
                    "verse": "aver di sue bellezze e di bontade,"
                },
                {
                    "verse": "né mi pensai nella primera etade"
                },
                {
                    "verse": "finisse in me per lei la mente afflitta,"
                },
                {
                    "verse": "che Venere trafitta"
                },
                {
                    "verse": "dal figlio m'assembrò, sì bella parse."
                },
                {
                    "verse": "Ella avie tutte isparse"
                },
                {
                    "verse": "all'alto Appollo le sue trezze bionde,"
                },
                {
                    "verse": "che fan parer quando un nugol s'asconde."
                }
            ],
            [
                {
                    "verse": "Oh, con quanta dolcezza e gran disio"
                },
                {
                    "verse": "d'una fiammetta soave e vivace"
                },
                {
                    "verse": "portai quel tempo in pace,"
                },
                {
                    "verse": "mentre piacque a colei ch'ebbe il cor mio!"
                },
                {
                    "verse": "Or d'ora in ora alla morte m'invio"
                },
                {
                    "verse": "e già veggio quel punto esser presente"
                },
                {
                    "verse": "che dal corpo dolente"
                },
                {
                    "verse": "partir convienmi e d'esta vita rea,"
                },
                {
                    "verse": "pel poter d'una iddea,"
                },
                {
                    "verse": "alla qual lungo tempo servo giacqui."
                },
                {
                    "verse": "Da lei mi tolse Amore, ond'io le spiacqui."
                }
            ],
            [
                {
                    "verse": "Lasso! ché quando di due parti l'una"
                },
                {
                    "verse": "presi, poi ch'io fu' preso, la più acerba,"
                },
                {
                    "verse": "per virtù di Minerva"
                },
                {
                    "verse": "si fé la donna mia di piatà ignuna,"
                },
                {
                    "verse": "di poi, più volte volto il sul, la luna,"
                },
                {
                    "verse": "costei ognor ver me più incrudelita:"
                },
                {
                    "verse": "però manca la vita,"
                },
                {
                    "verse": "ché Morte alle mie membra ha stese l'ale."
                },
                {
                    "verse": "Però lascio il mortale"
                },
                {
                    "verse": "corpo per terra e le voci meschine,"
                },
                {
                    "verse": "e sono al punto ove sarà mia fine."
                }
            ],
            [
                {
                    "verse": "Qui finirò tutti li miei martiri"
                },
                {
                    "verse": "omai, ché i membri son da Morte tolti;"
                },
                {
                    "verse": "però ciascun m'ascolti,"
                },
                {
                    "verse": "mentre che potrò dire, o donne e viri,"
                },
                {
                    "verse": "che l'aier piange già de' miei martiri."
                },
                {
                    "verse": "Giunta è la vita ove rimarrà spenta;"
                },
                {
                    "verse": "ogni persona il senta"
                },
                {
                    "verse": "ch'io moro a torto; e questo è ben palese,"
                },
                {
                    "verse": "ché, se Vener mi prese"
                },
                {
                    "verse": "da quella iddea e femmi altro seguire,"
                },
                {
                    "verse": "non fallai io, ché mi convien morire."
                },
                {
                    "verse": "— Canzone, come l'anima dal corpo"
                },
                {
                    "verse": "vedi partita, non ristar già mai,"
                },
                {
                    "verse": "ed a que' tai — n'andrai"
                },
                {
                    "verse": "ch'amor di donna non ebbe in lor corpo."
                },
                {
                    "verse": "Dirai come a gran torto"
                },
                {
                    "verse": "due celesti occhi stanno anzi al mio core."
                },
                {
                    "verse": "O servitor d'Amore,"
                },
                {
                    "verse": "se bene intendi tutto quel ch'i' scrivo,"
                },
                {
                    "verse": "piglia essemplo di me, che non son vivo!"
                }
            ]
        ]
    }
]